Workbook
Name aporte: Investimento_controle!$D$17
Name qtde_anos: Investimento_controle!$D$18
Name rendimento_carteira: Investimento_controle!$D$13
Name salario: Investimento_controle!$D$12
Name sugestao_investimento: Investimento_controle!$D$14
Name taxa_mensal: Investimento_controle!$D$19

Sheet Investimento_controle
B11: CONFIGURAÇÕES
B12: Salário | D12: 2000
B13: Rendimento Carteira | D13: 0.006
B14: Sugestão de Investimento ( 30% ) | D14: 600
B16: INVESTIMENTO MENSAL
B17: Quanto investir por mês? | D17: 200
B18: Por quantos anos? | D18: 5
B19: taxa de rendimento mensal? | D19: 0.01079
B20: Patrimônio acumulado? | D20: =FV(taxa_mensal,qtde_anos*12,aporte)*(-1) -> 16755.383
B21: Dividendos mensais? | D21: =D20*rendimento_carteira -> 100.5323
B23: CENÁRIOS | D23: Dividendos
A24: 2 | B24: Quanto em 2 anos? | C24: =FV(taxa_mensal,A24*12,aporte)*(-1) -> 5445.5255 | D24: =C24*rendimento_carteira -> 32.673153
A25: 5 | B25: Quanto em 5 anos? | C25: =FV(taxa_mensal,A25*12,aporte)*(-1) -> 16755.383 | D25: =C25*rendimento_carteira -> 100.5323
A26: 10 | B26: Quanto em 10 anos? | C26: =FV(taxa_mensal,A26*12,aporte)*(-1) -> 48656.843 | D26: =C26*rendimento_carteira -> 291.94106
A27: 20 | B27: Quanto em 20 anos? | C27: =FV(taxa_mensal,A27*12,aporte)*(-1) -> 225039.68 | D27: =C27*rendimento_carteira -> 1350.2381
A28: 30 | B28: Quanto em 30 anos? | C28: =FV(taxa_mensal,A28*12,aporte)*(-1) -> 864433.93 | D28: =C28*rendimento_carteira -> 5186.6036
B32: PERFIL | C32: Moderado
B33: VALOR A SER INVESTIDO POR MÊS | C33: =aporte -> 200
B35: TIPO DE FII | C35: Percentual Sugerido | D35: Valores
B36: PAPEL | C36: =VLOOKUP($C$32&"-"&B36,Planilha2!A:D,4,FALSE) -> 0.32 | D36: =C36*$C$33 -> 64
B37: TIJOLO | C37: =VLOOKUP($C$32&"-"&B37,Planilha2!A:D,4,FALSE) -> 0.35 | D37: =C37*$C$33 -> 70
B38: HIBRIDO | C38: =VLOOKUP($C$32&"-"&B38,Planilha2!A:D,4,FALSE) -> 0.08 | D38: =C38*$C$33 -> 16
B39: FOFs | C39: =VLOOKUP($C$32&"-"&B39,Planilha2!A:D,4,FALSE) -> 0.05 | D39: =C39*$C$33 -> 10
B40: DESENVOLVIMENTO | C40: =VLOOKUP($C$32&"-"&B40,Planilha2!A:D,4,FALSE) -> 0.1 | D40: =C40*$C$33 -> 20
B41: HOTELARIAS | C41: =VLOOKUP($C$32&"-"&B41,Planilha2!A:D,4,FALSE) -> 0.1 | D41: =C41*$C$33 -> 20
D42: =SUM(D36:D41) -> 200

Sheet Planilha2
A2: CHAVE | B2: PERFIL | C2: TIPO DE FII | D2: %
A3: =B3& "-"&C3 -> Conservador-PAPEL | B3: Conservador | C3: PAPEL | D3: 0.3
A4: =B4& "-"&C4 -> Conservador-TIJOLO | B4: Conservador | C4: TIJOLO | D4: 0.5
A5: =B5& "-"&C5 -> Conservador-HIBRIDO | B5: Conservador | C5: HIBRIDO | D5: 0.1
A6: =B6& "-"&C6 -> Conservador-FOFs | B6: Conservador | C6: FOFs | D6: 0.1
A7: =B7& "-"&C7 -> Conservador-DESENVOLVIMENTO | B7: Conservador | C7: DESENVOLVIMENTO | D7: 0
A8: =B8& "-"&C8 -> Conservador-HOTELARIAS | B8: Conservador | C8: HOTELARIAS | D8: 0
A9: =B9& "-"&C9 -> Moderado-PAPEL | B9: Moderado | C9: PAPEL | D9: 0.32
A10: =B10& "-"&C10 -> Moderado-TIJOLO | B10: Moderado | C10: TIJOLO | D10: 0.35
A11: =B11& "-"&C11 -> Moderado-HIBRIDO | B11: Moderado | C11: HIBRIDO | D11: 0.08
A12: =B12& "-"&C12 -> Moderado-FOFs | B12: Moderado | C12: FOFs | D12: 0.05
A13: =B13& "-"&C13 -> Moderado-DESENVOLVIMENTO | B13: Moderado | C13: DESENVOLVIMENTO | D13: 0.1
A14: =B14& "-"&C14 -> Moderado-HOTELARIAS | B14: Moderado | C14: HOTELARIAS | D14: 0.1
... A20: =B20& "-"&C20 -> Agressivo-HOTELARIAS | B20: Agressivo | C20: HOTELARIAS | D20: 0.1
